uciwebauth/__init__.py
uciwebauth/uciwebauth.py
uciwebauth-2022.9.28.dist-info/LICENSE
uciwebauth-2022.9.28.dist-info/METADATA
uciwebauth-2022.9.28.dist-info/WHEEL
uciwebauth-2022.9.28.dist-info/top_level.txt
uciwebauth-2022.9.28.dist-info/RECORD
