Metadata-Version: 2.1
Name: uciwebauth
Version: 2022.9.28
Summary: Access UCI WebAuth, LDAP person records, and Active Directory user objects
Home-page: https://www.cgohlke.com
Author: Christoph Gohlke
Author-email: cgohlke@cgohlke.com
License: BSD
Project-URL: Bug Tracker, https://github.com/cgohlke/uciwebauth/issues
Project-URL: Source Code, https://github.com/cgohlke/uciwebauth
Platform: any
Classifier: Development Status :: 4 - Beta
Classifier: License :: OSI Approved :: BSD License
Classifier: Intended Audience :: Developers
Classifier: Operating System :: OS Independent
Classifier: Programming Language :: Python :: 3 :: Only
Classifier: Programming Language :: Python :: 3.7
Classifier: Programming Language :: Python :: 3.8
Classifier: Programming Language :: Python :: 3.9
Classifier: Programming Language :: Python :: 3.10
Classifier: Programming Language :: Python :: 3.11
Requires-Python: >=3.7
License-File: LICENSE
Provides-Extra: adsi
Requires-Dist: pywin32 (>=300) ; (sys_platform == "win32" and platform_python_implementation != "PyPy") and extra == 'adsi'
Provides-Extra: all
Requires-Dist: python-ldap (>=3.3) ; extra == 'all'
Requires-Dist: pywin32 (>=300) ; (sys_platform == "win32" and platform_python_implementation != "PyPy") and extra == 'all'
Provides-Extra: ldap
Requires-Dist: python-ldap (>=3.3) ; extra == 'ldap'
